{
    "swagger": "2.0",
    "info": {
        "contact": {}
    },
    "paths": {
        "/docs": {
            "post": {
                "description": "create decrypted doc with signature",
                "consumes": [
                    "application/json"
                ],
                "produces": [
                    "application/json"
                ],
                "tags": [
                    "docs"
                ],
                "summary": "create decrypted doc with signature",
                "responses": {
                    "200": {
                        "description": "OK",
                        "schema": {
                            "type": "string"
                        }
                    },
                    "400": {
                        "description": "Bad Request",
                        "schema": {
                            "type": "string"
                        }
                    },
                    "500": {
                        "description": "Internal Server Error",
                        "schema": {
                            "type": "string"
                        }
                    }
                }
            }
        },
        "/docs/available": {
            "post": {
                "description": "get available docs for user",
                "consumes": [
                    "application/json"
                ],
                "produces": [
                    "application/json"
                ],
                "tags": [
                    "docs"
                ],
                "summary": "get available docs for user",
                "responses": {
                    "200": {
                        "description": "OK",
                        "schema": {
                            "type": "string"
                        }
                    },
                    "400": {
                        "description": "Bad Request",
                        "schema": {
                            "type": "string"
                        }
                    },
                    "500": {
                        "description": "Internal Server Error",
                        "schema": {
                            "type": "string"
                        }
                    }
                }
            }
        },
        "/docs/{doc_id}": {
            "get": {
                "description": "get document by doc_id",
                "consumes": [
                    "application/json"
                ],
                "produces": [
                    "application/json"
                ],
                "tags": [
                    "docs"
                ],
                "summary": "get document by doc_id",
                "parameters": [
                    {
                        "type": "string",
                        "description": "The doc_id of a document",
                        "name": "doc_id",
                        "in": "path",
                        "required": true
                    }
                ],
                "responses": {
                    "200": {
                        "description": "OK",
                        "schema": {
                            "type": "string"
                        }
                    },
                    "400": {
                        "description": "Bad Request",
                        "schema": {
                            "type": "string"
                        }
                    },
                    "500": {
                        "description": "Internal Server Error",
                        "schema": {
                            "type": "string"
                        }
                    }
                }
            }
        },
        "/keys": {
            "get": {
                "description": "get generated public and private keys for user from server",
                "consumes": [
                    "application/json"
                ],
                "produces": [
                    "application/json"
                ],
                "tags": [
                    "keys"
                ],
                "summary": "get generated public and private keys",
                "responses": {
                    "200": {
                        "description": "OK",
                        "schema": {
                            "type": "string"
                        }
                    },
                    "400": {
                        "description": "Bad Request",
                        "schema": {
                            "type": "string"
                        }
                    },
                    "500": {
                        "description": "Internal Server Error",
                        "schema": {
                            "type": "string"
                        }
                    }
                }
            }
        },
        "/keys/public": {
            "get": {
                "description": "get your public",
                "consumes": [
                    "application/json"
                ],
                "produces": [
                    "application/json"
                ],
                "tags": [
                    "keys"
                ],
                "summary": "get your public key",
                "responses": {
                    "200": {
                        "description": "OK",
                        "schema": {
                            "type": "string"
                        }
                    },
                    "400": {
                        "description": "Bad Request",
                        "schema": {
                            "type": "string"
                        }
                    },
                    "500": {
                        "description": "Internal Server Error",
                        "schema": {
                            "type": "string"
                        }
                    }
                }
            },
            "post": {
                "description": "post your public key in the system",
                "consumes": [
                    "application/json"
                ],
                "produces": [
                    "application/json"
                ],
                "tags": [
                    "keys"
                ],
                "summary": "post your public key in the system",
                "responses": {
                    "200": {
                        "description": "OK",
                        "schema": {
                            "type": "string"
                        }
                    },
                    "400": {
                        "description": "Bad Request",
                        "schema": {
                            "type": "string"
                        }
                    },
                    "500": {
                        "description": "Internal Server Error",
                        "schema": {
                            "type": "string"
                        }
                    }
                }
            }
        },
        "/keys/public/server": {
            "get": {
                "description": "get server public key",
                "consumes": [
                    "application/json"
                ],
                "produces": [
                    "application/json"
                ],
                "tags": [
                    "keys"
                ],
                "summary": "get server public key",
                "responses": {
                    "200": {
                        "description": "OK",
                        "schema": {
                            "type": "string"
                        }
                    },
                    "400": {
                        "description": "Bad Request",
                        "schema": {
                            "type": "string"
                        }
                    },
                    "500": {
                        "description": "Internal Server Error",
                        "schema": {
                            "type": "string"
                        }
                    }
                }
            }
        },
        "/keys/public/{user_id}": {
            "get": {
                "description": "get another user public key",
                "consumes": [
                    "application/json"
                ],
                "produces": [
                    "application/json"
                ],
                "tags": [
                    "keys"
                ],
                "summary": "get another user public key",
                "parameters": [
                    {
                        "type": "string",
                        "description": "The unique user_id of a User",
                        "name": "user_id",
                        "in": "path",
                        "required": true
                    }
                ],
                "responses": {
                    "200": {
                        "description": "OK",
                        "schema": {
                            "type": "string"
                        }
                    },
                    "400": {
                        "description": "Bad Request",
                        "schema": {
                            "type": "string"
                        }
                    },
                    "500": {
                        "description": "Internal Server Error",
                        "schema": {
                            "type": "string"
                        }
                    }
                }
            }
        }
    }
}